{
    "sponsors": [
        {
            "title": "Mountain View News",
            "url": "http://www.mtnviewsnews.com/"
        },
        {
            "title": "Allan Company Recycling Services",
            "url": "http://www.allancompany.com/"
        },
        {
            "title": "Best Buy Chemical & Supply Co",
            "url": "http://www.bestbuychemical.com/"
        },
        {
            "title": "Bolton & Company",
            "url": "http://www.boltonco.com/"
        },
        {
            "title": "Catherine Adde at Travelstore",
            "url": "http://www.travelstore.com/our-travel-experts/catherine-adde"
        },
        {
            "title": "Faulkner Design",
            "url": "http://jamesafaulkner.wix.com/faulknerdesign"
        },
        {
            "title": "Jeff Rudisill Audio",
            "url": ""
        },
        {
            "title": "LeVeque Construction",
            "url": "http://www.levequeconstruction.com/"
        },
        {
            "title": "Lucas & Horsfall Accountants & Advisors",
            "url": "http://www.lhmp.com/"
        },
        {
            "title": "McKenna Long & Aldridge LLP",
            "url": "http://mckennalong.com/"
        },
        {
            "title": "Montrose Travel",
            "url": "http://www.montrosetravel.com/"
        },
        {
            "title": "Perfumemart.com",
            "url": "http://www.perfumemart.com/"
        },
        {
            "title": "Play it Again Sports Pasadena",
            "url": "http://playitagainsports.com/"
        },
        {
            "title": "Scott Financial Group",
            "url": "http://www.bscottfinancialgroup.com/"
        },
        {
            "title": "TDG Digital - The Destination Group",
            "url": "http://www.dgrp.com/"
        },
        {
            "title": "The Hair Upstairs",
            "url": "http://www.thehairupstairs.com/"
        },
        {
            "title": "The Law Offices of Stephen J.Horvath",
            "url": "http://www.sjhtriallaw.com/"
        }
    ]
}